[{"stopId":1074,"lineId":"E3","isHead":"False","destination":"FELIPE II","busId":"7947","busTimeLeft":479,"busDistance":1111,"longitude":-3.59624368369,"latitude":40.401682041707,"busPositionType":1},{"stopId":1074,"lineId":"4","isHead":"False","destination":"CIUDAD LINEAL","busId":"5214","busTimeLeft":515,"busDistance":1129,"longitude":-3.5960219388361,"latitude":40.401215928178,"busPositionType":1},{"stopId":1074,"lineId":"106","isHead":"False","destination":"MANUEL BECERRA","busId":"5234","busTimeLeft":719,"busDistance":2294,"longitude":-3.5901715204197,"latitude":40.405846477901,"busPositionType":1},{"stopId":1074,"lineId":"E3","isHead":"False","destination":"FELIPE II","busId":"1002","busTimeLeft":1138,"busDistance":4162,"longitude":-3.6214364824399,"latitude":40.411581714433,"busPositionType":1},{"stopId":1074,"lineId":"4","isHead":"False","destination":"CIUDAD LINEAL","busId":"5237","busTimeLeft":999999,"busDistance":6807,"longitude":-3.6227331640478,"latitude":40.420269247217,"busPositionType":1},{"stopId":1074,"lineId":"106","isHead":"False","destination":"MANUEL BECERRA","busId":"5263","busTimeLeft":999999,"busDistance":5444,"longitude":-3.6130470399636,"latitude":40.406357660841,"busPositionType":1}]