[{"stopId":1571,"lineId":"124","isHead":"False","destination":"LACOMA","busId":"8311","busTimeLeft":16,"busDistance":50,"longitude":-3.7029183056301,"latitude":40.453638588559,"busPositionType":2},{"stopId":1571,"lineId":"128","isHead":"False","destination":"BARRIO DEL PILAR","busId":"6565","busTimeLeft":55,"busDistance":239,"longitude":-3.7032670212537,"latitude":40.451333060025,"busPositionType":2},{"stopId":1571,"lineId":"66","isHead":"False","destination":"FUENCARRAL","busId":"8157","busTimeLeft":147,"busDistance":394,"longitude":-3.7033252330657,"latitude":40.450964473476,"busPositionType":1},{"stopId":1571,"lineId":"126","isHead":"False","destination":"NUEVOS MINISTERIOS","busId":"8417","busTimeLeft":233,"busDistance":694,"longitude":-3.70974630412,"latitude":40.457144656119,"busPositionType":1},{"stopId":1571,"lineId":"66","isHead":"False","destination":"FUENCARRAL","busId":"8196","busTimeLeft":242,"busDistance":825,"longitude":-3.7038331952061,"latitude":40.447560999444,"busPositionType":1},{"stopId":1571,"lineId":"64","isHead":"False","destination":"PITIS","busId":"8611","busTimeLeft":371,"busDistance":1008,"longitude":-3.7031442159004,"latitude":40.447078711266,"busPositionType":1},{"stopId":1571,"lineId":"128","isHead":"False","destination":"BARRIO DEL PILAR","busId":"8401","busTimeLeft":412,"busDistance":1657,"longitude":-3.7028585180518,"latitude":40.45402633611,"busPositionType":1},{"stopId":1571,"lineId":"124","isHead":"False","destination":"LACOMA","busId":"8317","busTimeLeft":524,"busDistance":807,"longitude":-3.7033422277017,"latitude":40.446843273839,"busPositionType":1},{"stopId":1571,"lineId":"126","isHead":"False","destination":"NUEVOS MINISTERIOS","busId":"8412","busTimeLeft":930,"busDistance":3632,"longitude":-3.7121704416589,"latitude":40.472079803281,"busPositionType":1},{"stopId":1571,"lineId":"64","isHead":"False","destination":"PITIS","busId":"8612","busTimeLeft":1091,"busDistance":3265,"longitude":-3.7160756631784,"latitude":40.458720643621,"busPositionType":1}]