[{"stopId":2241,"lineId":"52","isHead":"False","destination":"SANTAMARCA","busId":"8262","busTimeLeft":90,"busDistance":341,"longitude":-3.6786904684733,"latitude":40.441013252224,"busPositionType":1},{"stopId":2241,"lineId":"29","isHead":"False","destination":"MANOTERAS","busId":"9229","busTimeLeft":250,"busDistance":797,"longitude":-3.6791253369318,"latitude":40.436729434576,"busPositionType":1},{"stopId":2241,"lineId":"52","isHead":"False","destination":"SANTAMARCA","busId":"8294","busTimeLeft":616,"busDistance":2081,"longitude":-3.6801336444951,"latitude":40.425005023563,"busPositionType":1},{"stopId":2241,"lineId":"29","isHead":"False","destination":"MANOTERAS","busId":"9211","busTimeLeft":909,"busDistance":2706,"longitude":-3.6761711823522,"latitude":40.423974044251,"busPositionType":1}]