[{"stopId":4421,"lineId":"140","isHead":"False","destination":"CANILLEJAS","busId":"7893","busTimeLeft":222,"busDistance":937,"longitude":-3.6045285746231,"latitude":40.427201049015,"busPositionType":1},{"stopId":4421,"lineId":"38","isHead":"False","destination":"MANUEL BECERRA","busId":"5261","busTimeLeft":286,"busDistance":1400,"longitude":-3.601607108154,"latitude":40.427097965007,"busPositionType":1},{"stopId":4421,"lineId":"38","isHead":"False","destination":"MANUEL BECERRA","busId":"5211","busTimeLeft":860,"busDistance":1922,"longitude":-3.6059820509453,"latitude":40.424845379835,"busPositionType":1},{"stopId":4421,"lineId":"140","isHead":"False","destination":"CANILLEJAS","busId":"7858","busTimeLeft":1126,"busDistance":5373,"longitude":-3.6351667899978,"latitude":40.399958926017,"busPositionType":1}]