[{"stopId":4886,"lineId":"104","isHead":"False","destination":"CIUDAD LINEAL","busId":"8190","busTimeLeft":450,"busDistance":2556,"longitude":-3.6386794634251,"latitude":40.469218592507,"busPositionType":1},{"stopId":4886,"lineId":"122","isHead":"False","destination":"AVENIDA AMERICA","busId":"8721","busTimeLeft":493,"busDistance":1499,"longitude":-3.6166457472856,"latitude":40.458738526598,"busPositionType":1},{"stopId":4886,"lineId":"112","isHead":"False","destination":"MAR DE CRISTAL","busId":"8480","busTimeLeft":725,"busDistance":5725,"longitude":-3.589424652796,"latitude":40.461721845042,"busPositionType":1},{"stopId":4886,"lineId":"122","isHead":"False","destination":"AVENIDA AMERICA","busId":"8726","busTimeLeft":1153,"busDistance":4442,"longitude":-3.6401576364915,"latitude":40.461358245146,"busPositionType":1},{"stopId":4886,"lineId":"104","isHead":"False","destination":"CIUDAD LINEAL","busId":"8815","busTimeLeft":1169,"busDistance":5998,"longitude":-3.6180536372459,"latitude":40.457001915758,"busPositionType":1},{"stopId":4886,"lineId":"112","isHead":"False","destination":"MAR DE CRISTAL","busId":"8705","busTimeLeft":999999,"busDistance":9477,"longitude":-3.5820793946263,"latitude":40.450302680919,"busPositionType":1}]